ebscopy/__init__.py
ebscopy/edsapi.py
ebscopy/tests/__init__.py
ebscopy/tests/edsapi_test.py.old
ebscopy/tests/test_edsapi.py
ebscopy-1.0.0.data/data/ebscopy/docs/INSTALL.md
ebscopy-1.0.0.data/data/ebscopy/docs/USAGE.md
ebscopy-1.0.0.data/data/ebscopy/samples/plain_old_test.py
ebscopy-1.0.0.data/data/ebscopy/samples/sample.ebscopy_env
ebscopy-1.0.0.dist-info/METADATA
ebscopy-1.0.0.dist-info/WHEEL
ebscopy-1.0.0.dist-info/licenses/LICENSE.txt
ebscopy-1.0.0.dist-info/RECORD
