Metadata-Version: 2.3
Name: ebscopy
Version: 1.0.0
Summary: Official Python wrapper for the EBSCO Discovery Service (EDS) API
Project-URL: Homepage, https://github.com/ebsco/ebscopy
Author-email: Jesse Jensen <jjensen@ebsco.com>, Olivia Muzzy <omuzzy@ebsco.com>
License:                     GNU GENERAL PUBLIC LICENSE
License-File: LICENSE.txt
Classifier: Intended Audience :: Developers
Classifier: Intended Audience :: Education
Classifier: License :: OSI Approved :: GNU General Public License v3 (GPLv3)
Classifier: Natural Language :: English
Classifier: Operating System :: OS Independent
Classifier: Programming Language :: Python
Classifier: Topic :: Internet :: WWW/HTTP :: Dynamic Content
Classifier: Topic :: Software Development :: Libraries
Classifier: Topic :: Software Development :: Libraries :: Python Modules
Requires-Python: >=3.12
Requires-Dist: lxml
Requires-Dist: python-dateutil
Requires-Dist: requests
